codedistutils2/__init__.py
codedistutils2/cat.py
codedistutils2/qwerty2/__init__.py
codedistutils2/qwerty2/dog.py
pypidisttest2-1.12.dist-info/LICENSE
pypidisttest2-1.12.dist-info/METADATA
pypidisttest2-1.12.dist-info/WHEEL
pypidisttest2-1.12.dist-info/top_level.txt
pypidisttest2-1.12.dist-info/RECORD
