Metadata-Version: 2.1
Name: pypidisttest2
Version: 1.12
Summary: Python Distribution Utilities
Home-page: https://www.python.org/sigs/
Author: Alexey Svetlov
Author-email: alexeysvetlov92@gmail.com
License: MIT
Project-URL: Source, https://github.com/32-52/yah2j
Platform: UNKNOWN
Classifier: Development Status :: 3 - Alpha
Classifier: Intended Audience :: Developers
Classifier: Topic :: Software Development :: Build Tools
Classifier: License :: OSI Approved :: MIT License
Classifier: Programming Language :: Python :: 3
Classifier: Programming Language :: Python :: 3.6
Classifier: Programming Language :: Python :: 3.7
Requires-Python: >=3.6
Requires-Dist: requests
